spandrel/__init__.py
spandrel/__helpers/__init__.py
spandrel/__helpers/canonicalize.py
spandrel/__helpers/loader.py
spandrel/__helpers/main_registry.py
spandrel/__helpers/model_descriptor.py
spandrel/__helpers/registry.py
spandrel/__helpers/size_req.py
spandrel/__helpers/unpickler.py
spandrel/architectures/__init__.py
spandrel/architectures/ATD/__init__.py
spandrel/architectures/ATD/__arch/__init__.py
spandrel/architectures/ATD/__arch/atd_arch.py
spandrel/architectures/CRAFT/__init__.py
spandrel/architectures/CRAFT/__arch/CRAFT.py
spandrel/architectures/CRAFT/__arch/__init__.py
spandrel/architectures/Compact/__init__.py
spandrel/architectures/Compact/__arch/SRVGG.py
spandrel/architectures/Compact/__arch/__init__.py
spandrel/architectures/DAT/__init__.py
spandrel/architectures/DAT/__arch/DAT.py
spandrel/architectures/DAT/__arch/__init__.py
spandrel/architectures/DCTLSA/__init__.py
spandrel/architectures/DCTLSA/__arch/__init__.py
spandrel/architectures/DCTLSA/__arch/dctlsa.py
spandrel/architectures/DITN/__init__.py
spandrel/architectures/DITN/__arch/DITN_Real.py
spandrel/architectures/DITN/__arch/__init__.py
spandrel/architectures/DRCT/__init__.py
spandrel/architectures/DRCT/__arch/__init__.py
spandrel/architectures/DRCT/__arch/drct_arch.py
spandrel/architectures/DRUNet/__init__.py
spandrel/architectures/DRUNet/__arch/__init__.py
spandrel/architectures/DRUNet/__arch/network_unet.py
spandrel/architectures/DnCNN/__init__.py
spandrel/architectures/DnCNN/__arch/__init__.py
spandrel/architectures/DnCNN/__arch/network_dncnn.py
spandrel/architectures/ESRGAN/__init__.py
spandrel/architectures/ESRGAN/__arch/RRDB.py
spandrel/architectures/ESRGAN/__arch/__init__.py
spandrel/architectures/FBCNN/__init__.py
spandrel/architectures/FBCNN/__arch/FBCNN.py
spandrel/architectures/FBCNN/__arch/__init__.py
spandrel/architectures/FFTformer/__init__.py
spandrel/architectures/FFTformer/__arch/__init__.py
spandrel/architectures/FFTformer/__arch/fftformer_arch.py
spandrel-0.4.0.dist-info/METADATA
spandrel-0.4.0.dist-info/WHEEL
spandrel-0.4.0.dist-info/top_level.txt
spandrel-0.4.0.dist-info/RECORD
