Metadata-Version: 2.1
Name: spandrel
Version: 0.4.0
Summary: Give your project support for a variety of PyTorch model architectures, including auto-detecting model architecture from just .pth files. spandrel gives you arch support.
Author: chaiNNer team
License: MIT
Keywords: spandrel,pytorch architecture,pytorch arch,model arch,model architecture
Classifier: Development Status :: 2 - Pre-Alpha
Classifier: Intended Audience :: Developers
Classifier: Topic :: Software Development :: Libraries
Classifier: Programming Language :: Python :: 3
Classifier: Programming Language :: Python :: 3.8
Classifier: Programming Language :: Python :: 3.9
Classifier: Programming Language :: Python :: 3.10
Classifier: Programming Language :: Python :: 3.11
Classifier: Programming Language :: Python :: 3.12
Classifier: Programming Language :: Python :: 3 :: Only
Classifier: License :: OSI Approved :: MIT License
Classifier: Operating System :: OS Independent
Requires-Python: >=3.8
Requires-Dist: torch
Requires-Dist: torchvision
Requires-Dist: safetensors
Requires-Dist: numpy
Requires-Dist: einops
Requires-Dist: typing-extensions
